{
  "updated_at": "2026-06-24T02:56:30.111334",
  "count": 20,
  "movies": [
    {
      "title": "ディッシュアップ",
      "url": "https://eiga.com/movie/105771/",
      "release_date": "6月20日",
      "thumbnail": "https://media.eiga.com/images/movie/105771/photo/3c07bd2686c5419a/320.jpg",
      "scraped_at": "2026-06-24T02:56:30.052553"
    },
    {
      "title": "愛の世紀",
      "url": "https://eiga.com/movie/1257/",
      "release_date": "6月20日",
      "thumbnail": "https://media.eiga.com/images/movie/1257/photo/91cb7b35795f7837/320.jpg",
      "scraped_at": "2026-06-24T02:56:30.052628"
    },
    {
      "title": "ゴダール・ソシアリスム",
      "url": "https://eiga.com/movie/55820/",
      "release_date": "6月20日",
      "thumbnail": "https://media.eiga.com/images/movie/55820/photo/d18b358fafb904d0/320.jpg",
      "scraped_at": "2026-06-24T02:56:30.052679"
    },
    {
      "title": "映画史特別編 選ばれた瞬間",
      "url": "https://eiga.com/movie/105872/",
      "release_date": "6月20日",
      "thumbnail": "https://media.eiga.com/images/movie/105872/photo/c8bbb84f019d8434/320.jpg",
      "scraped_at": "2026-06-24T02:56:30.052727"
    },
    {
      "title": "アワーミュージック",
      "url": "https://eiga.com/movie/1584/",
      "release_date": "6月20日",
      "thumbnail": "https://media.eiga.com/images/movie/1584/photo/00464b84cfe60b86/320.jpg",
      "scraped_at": "2026-06-24T02:56:30.052774"
    },
    {
      "title": "白衣の男",
      "url": "https://eiga.com/movie/106144/",
      "release_date": "6月20日",
      "thumbnail": "https://media.eiga.com/images/movie/106144/photo/12513c05f9e6e3e0/320.jpg",
      "scraped_at": "2026-06-24T02:56:30.052864"
    },
    {
      "title": "ラベンダー・ヒル・モブ",
      "url": "https://eiga.com/movie/106145/",
      "release_date": "6月20日",
      "thumbnail": "https://media.eiga.com/images/movie/106145/photo/03c21754f93c4abb/320.jpg",
      "scraped_at": "2026-06-24T02:56:30.052906"
    },
    {
      "title": "カインド・ハート",
      "url": "https://eiga.com/movie/106143/",
      "release_date": "6月20日",
      "thumbnail": "https://media.eiga.com/images/movie/106143/photo/4c7d5c10e8db72d1/320.jpg",
      "scraped_at": "2026-06-24T02:56:30.052950"
    },
    {
      "title": "最後通告",
      "url": "https://eiga.com/movie/44675/",
      "release_date": "6月20日",
      "thumbnail": "https://media.eiga.com/images/movie/44675/photo/3a36b60006a0ca2b/320.jpg",
      "scraped_at": "2026-06-24T02:56:30.052991"
    },
    {
      "title": "黒牢城",
      "url": "https://eiga.com/movie/105427/",
      "release_date": "6月19日",
      "thumbnail": "https://media.eiga.com/images/movie/105427/photo/a4101f785d3488eb/320.jpg",
      "scraped_at": "2026-06-24T02:56:30.053034"
    },
    {
      "title": "急に具合が悪くなる",
      "url": "https://eiga.com/movie/103908/",
      "release_date": "6月19日",
      "thumbnail": "https://media.eiga.com/images/movie/103908/photo/687f3afacff2f49c/320.jpg",
      "scraped_at": "2026-06-24T02:56:30.053072"
    },
    {
      "title": "免許返納!?",
      "url": "https://eiga.com/movie/105248/",
      "release_date": "6月19日",
      "thumbnail": "https://media.eiga.com/images/movie/105248/photo/ff72d6e0f86dc6be/320.jpg",
      "scraped_at": "2026-06-24T02:56:30.053108"
    },
    {
      "title": "マジカル・シークレット・ツアー",
      "url": "https://eiga.com/movie/105486/",
      "release_date": "6月19日",
      "thumbnail": "https://media.eiga.com/images/movie/105486/photo/b058d8412f865268/320.jpg",
      "scraped_at": "2026-06-24T02:56:30.053144"
    },
    {
      "title": "君は映画",
      "url": "https://eiga.com/movie/105232/",
      "release_date": "6月19日",
      "thumbnail": "https://media.eiga.com/images/movie/105232/photo/2f1c4eab956d794e/320.jpg",
      "scraped_at": "2026-06-24T02:56:30.053180"
    },
    {
      "title": "さよなら、僕の英雄",
      "url": "https://eiga.com/movie/105852/",
      "release_date": "6月19日",
      "thumbnail": "https://media.eiga.com/images/movie/105852/photo/7ddff95c6aa6283a/320.jpg",
      "scraped_at": "2026-06-24T02:56:30.053258"
    },
    {
      "title": "億万長者の不都合な終末",
      "url": "https://eiga.com/movie/105932/",
      "release_date": "6月19日",
      "thumbnail": "https://media.eiga.com/images/movie/105932/photo/f726442228100ee9/320.jpg",
      "scraped_at": "2026-06-24T02:56:30.053315"
    },
    {
      "title": "偏向報道",
      "url": "https://eiga.com/movie/106121/",
      "release_date": "6月19日",
      "thumbnail": "https://media.eiga.com/images/movie/106121/photo/3b76e0fc548edccb/320.jpg",
      "scraped_at": "2026-06-24T02:56:30.053355"
    },
    {
      "title": "遺愛",
      "url": "https://eiga.com/movie/105509/",
      "release_date": "6月19日",
      "thumbnail": "https://media.eiga.com/images/movie/105509/photo/a972562710d72239/320.jpg",
      "scraped_at": "2026-06-24T02:56:30.053394"
    },
    {
      "title": "アイ・ワズ・ア・ストレンジャー",
      "url": "https://eiga.com/movie/105981/",
      "release_date": "6月19日",
      "thumbnail": "https://media.eiga.com/images/movie/105981/photo/729ad70280edff83/320.jpg",
      "scraped_at": "2026-06-24T02:56:30.053431"
    },
    {
      "title": "魔女の宅急便（1989）",
      "url": "https://eiga.com/movie/28558/",
      "release_date": "6月19日",
      "thumbnail": "https://media.eiga.com/images/movie/28558/photo/75df6f927ea0aacc/320.jpg",
      "scraped_at": "2026-06-24T02:56:30.053466"
    }
  ]
}